Workbook

Sheet Dashboard
A1: RIEPILOGO PATRIMONIO
A3: Categoria | B3: Valore (€)
A4: Azioni | B4: =SUMIF(Azioni!A:A,"<>",Azioni!H:H)
A5: ETF | B5: =SUMIF(ETF!A:A,"<>",ETF!H:H)
A6: Bond | B6: =SUMIF(Bond!A:A,"<>",Bond!G:G)
A7: Fondi Comuni | B7: =SUMIF('Fondi Comuni'!A:A,"<>",'Fondi Comuni'!F:F)
A8: Conti & Liquidità | B8: =SUMIF('Conti & Liquidità'!A:A,"<>",'Conti & Liquidità'!C:C)
A9: TOTALE ATTIVO | B9: =SUM(B4:B8)
A11: Mutuo & Debiti | B11: =SUMIF('Mutuo & Debiti'!A:A,"<>",'Mutuo & Debiti'!C:C)
A12: TOTALE PASSIVO | B12: =B11
A14: PATRIMONIO NETTO | B14: =B9-B12

Sheet Azioni
A1: Ticker | B1: Nome | C1: Quantità | D1: Prezzo Carico (€) | E1: Prezzo Corrente (€) | F1: Valore Carico (€) | G1: Valore Corrente (€) | H1: P&L (€) | I1: P&L (%) | J1: Dividendi Ricevuti (€) | K1: Data Acquisto | L1: Note
E2: =IFERROR(GOOGLEFINANCE(A2,"price"),"") | F2: =IF(C2<>"",C2*D2,"") | G2: =IF(C2<>"",C2*E2,"") | H2: =IF(G2<>"",G2-F2,"") | I2: =IF(F2<>0,H2/F2*100,"")

Sheet ETF
A1: Ticker | B1: Nome | C1: Quantità | D1: Prezzo Carico (€) | E1: Prezzo Corrente (€) | F1: Valore Carico (€) | G1: Valore Corrente (€) | H1: P&L (€) | I1: P&L (%) | J1: Dividendi Ricevuti (€) | K1: Data Acquisto | L1: Note
E2: =IFERROR(GOOGLEFINANCE(A2,"price"),"") | F2: =IF(C2<>"",C2*D2,"") | G2: =IF(C2<>"",C2*E2,"") | H2: =IF(G2<>"",G2-F2,"") | I2: =IF(F2<>0,H2/F2*100,"")

Sheet Bond
A1: Nome/ISIN | B1: Valore Nominale (€) | C1: Prezzo Acquisto (%) | D1: Data Acquisto | E1: Scadenza | F1: Cedola (%) | G1: Frequenza Cedole | H1: Valore Corrente (€) | I1: Rendimento YTM (%) | J1: Cedole Incassate (€) | K1: Note
H2: =IF(B2<>"",B2*(C2/100),"")

Sheet Fondi Comuni
A1: Nome Fondo | B1: ISIN | C1: Quote | D1: Prezzo Carico (€) | E1: Prezzo Corrente (€) | F1: Valore Corrente (€) | G1: P&L (€) | H1: P&L (%) | I1: Data Acquisto | J1: Note
F2: =IF(C2<>"",C2*E2,"") | G2: =IF(F2<>"",F2-(C2*D2),"") | H2: =IF(C2*D2<>0,G2/(C2*D2)*100,"")

Sheet Conti & Liquidità
A1: Nome Conto/Banca | B1: Tipo | C1: Saldo (€) | D1: Tasso Interesse (%) | E1: Scadenza Vincolo | F1: Interessi Maturati (€) | G1: Note
B2: Conto Corrente
B3: Deposito Libero
B4: Deposito Vincolato

Sheet Mutuo & Debiti
A1: Tipo Debito | B1: Importo Iniziale (€) | C1: Debito Residuo (€) | D1: Tasso Interesse (%) | E1: Rata Mensile (€) | F1: Data Inizio | G1: Scadenza | H1: Note

Sheet Stipendi
A1: Anno | B1: Mese | C1: Stipendio Lordo (€) | D1: Stipendio Netto (€) | E1: Bonus/Extra (€) | F1: Totale Netto (€) | G1: Note
A2: 2025 | B2: Gennaio | F2: =IF(D2<>"",D2+E2,"")
A3: 2025 | B3: Febbraio
A4: 2025 | B4: Marzo
A5: 2025 | B5: Aprile
A6: 2025 | B6: Maggio
A7: 2025 | B7: Giugno
A8: 2025 | B8: Luglio
A9: 2025 | B9: Agosto
A10: 2025 | B10: Settembre
A11: 2025 | B11: Ottobre
A12: 2025 | B12: Novembre
A13: 2025 | B13: Dicembre

Sheet Spese Mensili
A1: Anno | B1: Mese | C1: Affitto/Mutuo (€) | D1: Bollette (€) | E1: Spesa (€) | F1: Trasporti (€) | G1: Assicurazioni (€) | H1: Abbonamenti (€) | I1: Svago (€) | J1: Altro (€) | K1: TOTALE (€) | L1: Note
A2: 2025 | B2: Gennaio | K2: =SUM(C2:J2)
A3: 2025 | B3: Febbraio
A4: 2025 | B4: Marzo
A5: 2025 | B5: Aprile
A6: 2025 | B6: Maggio
A7: 2025 | B7: Giugno
A8: 2025 | B8: Luglio
A9: 2025 | B9: Agosto
A10: 2025 | B10: Settembre
A11: 2025 | B11: Ottobre
A12: 2025 | B12: Novembre
A13: 2025 | B13: Dicembre

Sheet Tasse
A1: Anno Fiscale | B1: Tipo | C1: Descrizione | D1: Base Imponibile (€) | E1: Aliquota (%) | F1: Importo Pagato (€) | G1: Data Pagamento | H1: Note
B2: Capital Gain | F2: =IF(D2<>"",D2*(E2/100),"")
B3: Dividendi
B4: Interessi

Sheet Storico Patrimonio
A1: Data | B1: Azioni | C1: ETF | D1: Bond | E1: Fondi | F1: Liquidità | G1: Totale Attivo | H1: Debiti | I1: Patrimonio Netto | J1: Var. % Mensile
G2: =SUM(B2:F2) | I2: =G2-H2 | J2: =IF(I1<>0,(I2-I1)/I1*100,"")
